{
	"name": "demoscheduletrigger",
	"properties": {
		"description": "daily",
		"annotations": [],
		"runtimeState": "Started",
		"pipelines": [
			{
				"pipelineReference": {
					"referenceName": "copydata",
					"type": "PipelineReference"
				}
			}
		],
		"type": "ScheduleTrigger",
		"typeProperties": {
			"recurrence": {
				"frequency": "Day",
				"interval": 1,
				"startTime": "2023-06-15T12:11:00Z",
				"endTime": "2023-06-16T12:11:00Z",
				"timeZone": "UTC",
				"schedule": {
					"minutes": [
						0
					],
					"hours": [
						10
					]
				}
			}
		}
	}
}